m_pyutil/__init__.py
m_pyutil/definitions.py
m_pyutil/mdate.py
m_pyutil/mhttp.py
m_pyutil/mip.py
m_pyutil/mjuliangip.py
m_pyutil/mmongo.py
m_pyutil/msqlite.py
m_pyutil/mtencent_map.py
m_pyutil/mtmp.py
m_pyutil/selenium/__init__.py
m_pyutil/selenium/mchrome.py
m_pyutil/selenium/moperator.py
tests/__init__.py
tests/test_mdate.py
tests/test_mhttp.py
tests/test_mip.py
tests/test_mjuliangip.py
tests/test_mmongo.py
tests/test_msqlite.py
tests/test_mtencent_map.py
tests/selenium/__init__.py
tests/selenium/test_mchrome.py
m_pyutil-1.9.3.dist-info/LICENSE
m_pyutil-1.9.3.dist-info/METADATA
m_pyutil-1.9.3.dist-info/WHEEL
m_pyutil-1.9.3.dist-info/top_level.txt
m_pyutil-1.9.3.dist-info/RECORD
